discordlib
